Metadata-Version: 2.1
Name: CleanGhostImages
Version: 0.2.0
Summary: A tool to find unused images in the Ghost blog content directory
Home-page: https://github.com/ixonae/CleanGhostImages
Author: Ixonae
Author-email: contact@ixonae.com
License: GNU GENERAL PUBLIC LICENSE v2
Requires-Python: >=3.6
License-File: LICENSE
